tornadowhois
