Metadata-Version: 1.1
Name: tornado-whois
Version: 0.8.1
Summary: Asynchronous python tornado whois client
Home-page: https://github.com/mehmetkose/tornado-whois
Author: Mehmet Kose
Author-email: mehmet.py@gmail.com
License: MIT
Keywords: tornado,whois,tornado-whois,async
Platform: UNKNOWN
Classifier: Programming Language :: Python :: 3 :: Only
Classifier: Programming Language :: Python :: 3.5
Classifier: Programming Language :: Python :: 3.6
Classifier: License :: OSI Approved :: MIT License
Requires: tornado (>=4.3)
